{
  "users": {
    "demo-user": {
      "config": {
        "background": "/dice/backgrounds/WhiteBackground.svg",
        "dice": "/dice/dice/WhiteDice.svg",
        "pattern": "/dice/patterns/1-2-3.svg",
        "accessories": null,
        "hat": null,
        "item": null,
        "companion": null
      },
      "updatedAt": "2025-08-29T20:55:44.586Z"
    },
    "cmfvf8x0y0000vbpvu6bgokym": {
      "config": {
        "background": "/dice/Backgrounds/WhiteBackground.svg",
        "dice": "/dice/Dice/WhiteDice.svg",
        "pattern": null,
        "accessories": null,
        "hat": null,
        "item": null,
        "companion": null,
        "title": null
      },
      "updatedAt": "2025-09-22T20:30:34.950Z"
    },
    "cmg88zsa300017kbsvllkpdof": {
      "config": {
        "background": "/dice/Backgrounds/BlackBackground.svg",
        "dice": "/dice/Dice/WhiteDice.svg",
        "pattern": "/dice/Patterns/1-2-3.svg",
        "accessories": null,
        "hat": null,
        "item": null,
        "companion": null,
        "title": "/dice/Titles/Commoner.svg"
      },
      "updatedAt": "2025-10-09T18:25:26.590Z"
    }
  }
}